vtacML/__init__.py
vtacML/evaluate_best_model.py
vtacML/models.py
vtacML/pipeline.py
vtacML/predict.py
vtacML/preparation.py
vtacML/search_best_model.py
vtacML/utils.py
vtacML/config/config.yaml
vtacML/data/combined_qpo_vt_all_cases_with_GRB_with_flags.parquet
vtacML-0.1.19.dist-info/LICENSE
vtacML-0.1.19.dist-info/METADATA
vtacML-0.1.19.dist-info/WHEEL
vtacML-0.1.19.dist-info/top_level.txt
vtacML-0.1.19.dist-info/RECORD
