Metadata-Version: 2.1
Name: vtacML
Version: 0.1.19
Summary: A machine learning pipeline to classify objects in VTAC dataset as GRB or not.
Home-page: https://github.com/jerbeario/VTAC_ML
Author: Jeremy Palmerio
Author-email: jeremypalmerio05@gmail.com
License: MIT
Classifier: Programming Language :: Python :: 3
Classifier: License :: OSI Approved :: MIT License
Classifier: Operating System :: OS Independent
Requires-Python: >=3.10
License-File: LICENSE
Requires-Dist: numpy==1.26.3
Requires-Dist: matplotlib==3.8.0
Requires-Dist: pandas==2.1.4
Requires-Dist: scikit-learn==1.3.0
Requires-Dist: seaborn==0.12.2
Requires-Dist: yellowbrick==1.5
Requires-Dist: pyyaml==6.0.1
Requires-Dist: imblearn==0.0
Requires-Dist: fastparquet==2023.8.0
Requires-Dist: joblib==1.2.0
Provides-Extra: dev
Requires-Dist: pytest==8.0.1; extra == "dev"
Requires-Dist: pylint==3.2.6; extra == "dev"
Requires-Dist: black==24.4.2; extra == "dev"
